fragalysis_api/__init__.py
fragalysis_api/xcimporter_utils.py
fragalysis_api/xcanalyser/__init__.py
fragalysis_api/xcanalyser/graphcreator.py
fragalysis_api/xcanalyser/xcanalyser.py
fragalysis_api/xcextracter/__init__.py
fragalysis_api/xcextracter/computed_set_update.py
fragalysis_api/xcextracter/frag_web_live.py
fragalysis_api/xcextracter/get_target_data.py
fragalysis_api/xcextracter/getdata.py
fragalysis_api/xcextracter/setup_molecule.py
fragalysis_api/xcextracter/xcextracter.py
fragalysis_api/xcglobalscripts/__init__.py
fragalysis_api/xcglobalscripts/set_config.py
fragalysis_api/xcimporter/__init__.py
fragalysis_api/xcimporter/align.py
fragalysis_api/xcimporter/conversion_pdb_mol.py
fragalysis_api/xcimporter/feature_extract.py
fragalysis_api/xcimporter/pdbimporter.py
fragalysis_api/xcimporter/pdbquery.py
fragalysis_api/xcimporter/solv_and_ions.py
fragalysis_api/xcimporter/validate.py
fragalysis_api/xcimporter/xc_utils.py
fragalysis_api/xcimporter/xcimporter.py
tests/__init__.py
tests/test_frag_website.py
tests/xcextractor/__init__.py
tests/xcextractor/test_GetMoleculesData.py
tests/xcextractor/test_GetPdbData.py
tests/xcextractor/test_GetTargetsData.py
tests/xcextractor/test_GraphRequest.py
tests/xcimporter/__init__.py
tests/xcimporter/test_align.py
tests/xcimporter/test_conversion.py
tests/xcimporter/test_pdb.py
tests/xcimporter/test_pdb_query.py
tests/xcimporter/test_validate.py
tests/xcimporter/test_xc_utils.py
tests/xcimporter/test_xcimporter.py
fragalysis_api-0.1.1.dist-info/LICENSE
fragalysis_api-0.1.1.dist-info/METADATA
fragalysis_api-0.1.1.dist-info/WHEEL
fragalysis_api-0.1.1.dist-info/top_level.txt
fragalysis_api-0.1.1.dist-info/RECORD
