Metadata-Version: 2.1
Name: fragalysis-api
Version: 0.1.1
Summary: An API for with working with Fragalysis data.
Home-page: https://github.com/xchem/fragalysis-api
Author: Fragment 5
Author-email: 
License: UNKNOWN
Platform: UNKNOWN
Classifier: Development Status :: 4 - Beta
Classifier: Programming Language :: Python :: 3.7
Classifier: License :: OSI Approved :: MIT License
Classifier: Operating System :: OS Independent
Requires-Python: >=3.6
Requires-Dist: biopython
Requires-Dist: numpy
Requires-Dist: pandas
Requires-Dist: pypdb
Requires-Dist: matplotlib
